edat_utils/__init__.py
edat_utils/edat_keycloak_service.py
edat_utils/edat_log_service.py
edat_utils/edat_slack_service.py
edat_utils/generic_controller.py
edat_utils/keycloak_service.py
edat_utils/planilha_helper.py
edat_utils/query_builder.py
edat_utils/query_runner.py
edat_utils/schema.py
edat_utils/utils.py
edat_utils/api/__init__.py
edat_utils/api/base.py
edat_utils/api/custom_exceptions.py
edat_utils/api/models.py
edat_utils/api/usuario_service.py
edat_utils/api/api_academico_service/__init__.py
edat_utils/api/api_academico_service/service.py
edat_utils/api/api_colegios_service/__init__.py
edat_utils/api/api_colegios_service/service.py
edat_utils/api/api_dac_service/__init__.py
edat_utils/api/api_dac_service/service.py
edat_utils/api/api_funcionario_service/__init__.py
edat_utils/api/api_funcionario_service/service.py
edat_utils/api/api_lotacao_service/__init__.py
edat_utils/api/api_lotacao_service/service.py
edat_utils/api/api_unidade_service/__init__.py
edat_utils/api/api_unidade_service/service.py
edat_utils/v2/__init__.py
edat_utils/v2/base_http.py
edat_utils/v2/base_http_service.py
edat_utils/v2/crud_base.py
edat_utils/v2/errors_handler.py
edat_utils/v2/funcao_service.py
edat_utils/v2/funcionario_service.py
edat_utils/v2/graphql_service.py
edat_utils/v2/lotacao_service.py
edat_utils/v2/models.py
edat_utils/v2/crud/__init__.py
edat_utils/v2/crud/crud_base.py
tests/__init__.py
tests/conftest.py
tests/api/__init__.py
tests/api/test_api_academico_service.py
tests/api/test_api_colegios_tecnicos_service.py
tests/api/test_api_dac_service.py
tests/api/test_api_funcionario_service.py
tests/api/test_api_lotacao_service.py
tests/api/test_api_unidade_service.py
tests/keycloak/__init__.py
tests/keycloak/test_edat_keycloak.py
tests/keycloak/test_keycloak.py
edat_utils-1.4.3.dist-info/METADATA
edat_utils-1.4.3.dist-info/WHEEL
edat_utils-1.4.3.dist-info/top_level.txt
edat_utils-1.4.3.dist-info/RECORD
