Metadata-Version: 2.1
Name: edat-utils
Version: 1.4.3
Summary: Biblioteca de Apoio ao desenvolvimento no EDAT
Home-page: UNKNOWN
Author: Escritório de Dados
Author-email: dados@unicamp.br
License: MIT
Platform: UNKNOWN
Classifier: Intended Audience :: Developers
Classifier: License :: OSI Approved :: MIT License
Classifier: Programming Language :: Python
Classifier: Operating System :: OS Independent
Requires-Dist: trino
Requires-Dist: SQLAlchemy
Requires-Dist: python-decouple
Requires-Dist: strawberry-graphql
